flagged_csv/__init__.py
flagged_csv/cli.py
flagged_csv/converter.py
flagged_csv/formatter.py
flagged_csv-0.1.5.dist-info/licenses/LICENSE
flagged_csv-0.1.5.dist-info/METADATA
flagged_csv-0.1.5.dist-info/WHEEL
flagged_csv-0.1.5.dist-info/entry_points.txt
flagged_csv-0.1.5.dist-info/top_level.txt
flagged_csv-0.1.5.dist-info/RECORD
