Metadata-Version: 2.4
Name: flagged-csv
Version: 0.1.5
Summary: Convert XLSX files to CSV with visual formatting preserved as inline flags
Author-email: ross <ross.jill.websolution@gmail.com>
License-Expression: MIT
Project-URL: Homepage, https://github.com/ross-jill-ws/flagged-csv
Project-URL: Documentation, https://github.com/ross-jill-ws/flagged-csv#readme
Project-URL: Repository, https://github.com/ross-jill-ws/flagged-csv.git
Project-URL: Issues, https://github.com/ross-jill-ws/flagged-csv/issues
Keywords: xlsx,csv,excel,converter,formatting,colors,merge-cells,ai,data-processing
Classifier: Development Status :: 4 - Beta
Classifier: Intended Audience :: Developers
Classifier: Intended Audience :: Science/Research
Classifier: Programming Language :: Python :: 3
Classifier: Programming Language :: Python :: 3.11
Classifier: Programming Language :: Python :: 3.12
Classifier: Topic :: Office/Business :: Financial :: Spreadsheet
Classifier: Topic :: Software Development :: Libraries :: Python Modules
Classifier: Topic :: Scientific/Engineering :: Information Analysis
Classifier: Operating System :: OS Independent
Requires-Python: >=3.11
License-File: LICENSE
Requires-Dist: numpy<2.0
Requires-Dist: pandas<2.2.0,>=2.0.0
Requires-Dist: pydantic>=2.0.0
Requires-Dist: openpyxl>=3.1.0
Requires-Dist: python-calamine>=0.2.0
Requires-Dist: xlrd>=2.0.0
Requires-Dist: click>=8.0.0
Requires-Dist: tabulate>=0.9.0
Dynamic: license-file
